{
  "version": "1.0",
  "date_mise_a_jour": "2024-01",
  "source": "MINSANTE Cameroun + FOSA 2023",
  "structures": [
    {
      "id": "HD_NGAOUNDERE_01",
      "type": "Hôpital de District",
      "nom": "Hôpital de District de Ngaoundéré",
      "region": "adamaoua",
      "district": "ngaoundere_urbain",
      "ville": "Ngaoundéré",
      "telephone": "+237 222 25 10 XX",
      "latitude": 7.3233,
      "longitude": 13.5833,
      "services": ["urgences_24h", "pediatrie", "maternite", "chirurgie", "laboratoire", "radiologie", "paludisme_grave", "malnutrition"],
      "lits": 120,
      "medecin_present": true
    },
    {
      "id": "CMA_NGAOUNDERE_01",
      "type": "CMA",
      "nom": "Centre Médical d'Arrondissement de Ngaoundéré Rural",
      "region": "adamaoua",
      "district": "ngaoundere_rural",
      "ville": "Ngaoundéré",
      "telephone": "+237 222 25 XX XX",
      "latitude": 7.3400,
      "longitude": 13.5600,
      "services": ["consultations", "pediatrie", "maternite", "paludisme", "malnutrition_simple"],
      "lits": 25,
      "medecin_present": false
    },
    {
      "id": "CDTB_NGAOUNDERE_01",
      "type": "CDTB",
      "nom": "Centre de Diagnostic et Traitement de la Tuberculose Ngaoundéré",
      "region": "adamaoua",
      "district": "ngaoundere_urbain",
      "ville": "Ngaoundéré",
      "telephone": "+237 222 25 XX XX",
      "latitude": 7.3200,
      "longitude": 13.5850,
      "services": ["diagnostic_tb", "traitement_dots", "crachat_baar"],
      "lits": 20,
      "medecin_present": true,
      "note": "Référence TB obligatoire pour toute la région Adamaoua"
    },
    {
      "id": "CRENAS_NGAOUNDERE_01",
      "type": "CRENAS",
      "nom": "Centre de Récupération et Éducation Nutritionnelle Ambulatoire Sévère de Ngaoundéré",
      "region": "adamaoua",
      "district": "ngaoundere_urbain",
      "ville": "Ngaoundéré",
      "telephone": "+237 222 25 XX XX",
      "latitude": 7.3250,
      "longitude": 13.5700,
      "services": ["malnutrition_mas_sans_complication", "atpe", "suivi_nutritionnel"],
      "lits": 0,
      "ambulatoire": true,
      "medecin_present": false
    },
    {
      "id": "CMA_MEIGANGA_01",
      "type": "CMA",
      "nom": "Centre Médical d'Arrondissement de Meiganga",
      "region": "adamaoua",
      "district": "meiganga",
      "ville": "Meiganga",
      "telephone": "+237 222 25 XX XX",
      "latitude": 6.5167,
      "longitude": 14.2833,
      "services": ["consultations", "pediatrie", "maternite", "paludisme"],
      "lits": 18,
      "medecin_present": false
    },
    {
      "id": "CMA_TIBATI_01",
      "type": "CMA",
      "nom": "Centre Médical d'Arrondissement de Tibati",
      "region": "adamaoua",
      "district": "tibati",
      "ville": "Tibati",
      "telephone": "+237 222 XX XX XX",
      "latitude": 6.4700,
      "longitude": 12.6200,
      "services": ["consultations", "pediatrie", "maternite", "urgences"],
      "lits": 15,
      "medecin_present": false
    },
    {
      "id": "CMA_BANYO_01",
      "type": "CMA",
      "nom": "Centre Médical d'Arrondissement de Banyo",
      "region": "adamaoua",
      "district": "banyo",
      "ville": "Banyo",
      "telephone": "+237 222 XX XX XX",
      "latitude": 6.7667,
      "longitude": 11.8167,
      "services": ["consultations", "urgences", "maternite"],
      "lits": 12,
      "medecin_present": false
    },
    {
      "id": "HD_BERTOUA_01",
      "type": "Hôpital de District",
      "nom": "Hôpital Régional de Bertoua",
      "region": "est_cameroun",
      "district": "bertoua",
      "ville": "Bertoua",
      "telephone": "+237 222 24 XX XX",
      "latitude": 4.5789,
      "longitude": 13.6850,
      "services": ["urgences_24h", "pediatrie", "maternite", "chirurgie", "laboratoire", "radiologie", "tb", "malnutrition", "vih"],
      "lits": 145,
      "medecin_present": true
    },
    {
      "id": "CDTB_BERTOUA_01",
      "type": "CDTB",
      "nom": "Centre de Diagnostic et Traitement de la Tuberculose Bertoua",
      "region": "est_cameroun",
      "district": "bertoua",
      "ville": "Bertoua",
      "telephone": "+237 222 24 XX XX",
      "latitude": 4.5850,
      "longitude": 13.6900,
      "services": ["diagnostic_tb", "traitement_dots", "crachat_baar", "culture_tb"],
      "lits": 30,
      "medecin_present": true,
      "note": "Principal CDTB de la région Est — référence obligatoire"
    },
    {
      "id": "CDTB_BATOURI_01",
      "type": "CDTB",
      "nom": "Centre de Diagnostic et Traitement de la Tuberculose Batouri",
      "region": "est_cameroun",
      "district": "batouri",
      "ville": "Batouri",
      "telephone": "+237 222 XX XX XX",
      "latitude": 4.4333,
      "longitude": 14.3667,
      "services": ["diagnostic_tb", "traitement_dots", "crachat_baar"],
      "lits": 15,
      "medecin_present": false
    },
    {
      "id": "CRENAS_BERTOUA_01",
      "type": "CRENAS",
      "nom": "Centre de Récupération Nutritionnelle Ambulatoire de Bertoua",
      "region": "est_cameroun",
      "district": "bertoua",
      "ville": "Bertoua",
      "telephone": "+237 222 24 XX XX",
      "latitude": 4.5750,
      "longitude": 13.6800,
      "services": ["malnutrition_mas", "atpe", "suivi_nutritionnel"],
      "lits": 0,
      "ambulatoire": true
    },
    {
      "id": "CRENI_BERTOUA_01",
      "type": "CRENI",
      "nom": "Centre de Récupération et Éducation Nutritionnelle Intensive de Bertoua",
      "region": "est_cameroun",
      "district": "bertoua",
      "ville": "Bertoua",
      "telephone": "+237 222 24 XX XX",
      "latitude": 4.5800,
      "longitude": 13.6850,
      "services": ["malnutrition_mas_complications", "hospitalisation_nutritionnelle", "f75_f100"],
      "lits": 20,
      "medecin_present": true,
      "note": "Seul CRENI de la région — malnutrition avec complications médicales"
    },
    {
      "id": "CMA_BATOURI_01",
      "type": "CMA",
      "nom": "Centre Médical d'Arrondissement de Batouri",
      "region": "est_cameroun",
      "district": "batouri",
      "ville": "Batouri",
      "telephone": "+237 222 XX XX XX",
      "latitude": 4.4333,
      "longitude": 14.3667,
      "services": ["consultations", "urgences", "pediatrie", "maternite"],
      "lits": 20,
      "medecin_present": false
    },
    {
      "id": "CMA_YOKADOUMA_01",
      "type": "CMA",
      "nom": "Centre Médical d'Arrondissement de Yokadouma",
      "region": "est_cameroun",
      "district": "yokadouma",
      "ville": "Yokadouma",
      "telephone": "+237 222 XX XX XX",
      "latitude": 3.5167,
      "longitude": 15.0500,
      "services": ["consultations", "urgences", "pediatrie", "maternite"],
      "lits": 16,
      "medecin_present": false,
      "note": "Zone forestière — accès difficile en saison des pluies"
    },
    {
      "id": "CMA_ABONG_MBANG_01",
      "type": "CMA",
      "nom": "Centre Médical d'Arrondissement d'Abong Mbang",
      "region": "est_cameroun",
      "district": "abong_mbang",
      "ville": "Abong Mbang",
      "telephone": "+237 222 XX XX XX",
      "latitude": 3.9833,
      "longitude": 13.1833,
      "services": ["consultations", "urgences", "maternite"],
      "lits": 14,
      "medecin_present": false
    },
    {
      "id": "CS_GADO_BADZERE_01",
      "type": "Centre de Santé",
      "nom": "Centre de Santé Camp Réfugiés Gado-Badzere (UNHCR/MSF)",
      "region": "est_cameroun",
      "district": "bertoua",
      "ville": "Gado-Badzere",
      "telephone": "+237 699 XX XX XX",
      "latitude": 4.7200,
      "longitude": 13.8500,
      "services": ["urgences", "pediatrie", "nutrition", "vih", "tb"],
      "lits": 30,
      "medecin_present": true,
      "gestionnaire": "UNHCR/MSF",
      "note": "Centre pour réfugiés RCA — 45 000 réfugiés enregistrés"
    }
  ],
  "contacts_urgences": {
    "samu_national": "119",
    "district_adamaoua": "+237 222 25 XX XX",
    "district_est_cameroun": "+237 222 24 XX XX",
    "minsante_alerte_epidemique": "+237 222 22 XX XX"
  }
}
